autofiles/__init__.py
autofiles/cli_action.py
autofiles/conftest.py
autofiles/file_extension.py
autofiles/main.py
autofiles/test_cli.py
autofiles/test_utils.py
autofiles/utils.py
slimebones_autofiles-0.1.2.dist-info/LICENSE
slimebones_autofiles-0.1.2.dist-info/METADATA
slimebones_autofiles-0.1.2.dist-info/WHEEL
slimebones_autofiles-0.1.2.dist-info/entry_points.txt
slimebones_autofiles-0.1.2.dist-info/RECORD
