Metadata-Version: 2.1
Name: slimebones-autofiles
Version: 0.1.2
Summary: 
Author: ryzhovalex
Author-email: thed4rkof@gmail.com
Requires-Python: >=3.11,<4.0
Classifier: Programming Language :: Python :: 3
Classifier: Programming Language :: Python :: 3.11
Requires-Dist: slimebones-pykit (>=0.4.14,<0.5.0)
